LICENSE
MANIFEST.in
README.md
requirements.txt
setup.py
hddfancontrol/__init__.py
hddfancontrol/__main__.py
hddfancontrol/bin_dep.py
hddfancontrol/colored_logging.py
hddfancontrol.egg-info/PKG-INFO
hddfancontrol.egg-info/SOURCES.txt
hddfancontrol.egg-info/dependency_links.txt
hddfancontrol.egg-info/entry_points.txt
hddfancontrol.egg-info/requires.txt
hddfancontrol.egg-info/top_level.txt