Metadata-Version: 1.1
Name: hddfancontrol
Version: 1.2.8
Summary: Control system fan speed by monitoring hard drive temperature
Home-page: https://github.com/desbma/hddfancontrol
Author: desbma
Author-email: UNKNOWN
License: UNKNOWN
Download-URL: https://github.com/desbma/hddfancontrol/archive/1.2.8.tar.gz
Keywords: hdd,drive,temperature,fan,control,speed
Platform: UNKNOWN
Classifier: Development Status :: 5 - Production/Stable
Classifier: Environment :: Console
Classifier: Environment :: No Input/Output (Daemon)
Classifier: Intended Audience :: End Users/Desktop
Classifier: Intended Audience :: System Administrators
Classifier: License :: OSI Approved :: GNU General Public License v3 (GPLv3)
Classifier: Natural Language :: English
Classifier: Operating System :: POSIX :: Linux
Classifier: Programming Language :: Python
Classifier: Programming Language :: Python :: 3
Classifier: Programming Language :: Python :: 3 :: Only
Classifier: Programming Language :: Python :: 3.3
Classifier: Programming Language :: Python :: 3.4
Classifier: Programming Language :: Python :: 3.5
Classifier: Programming Language :: Python :: 3.6
Classifier: Topic :: System :: Hardware
Classifier: Topic :: System :: Monitoring
Classifier: Topic :: Utilities
